{
  "annotations": {
    "list": [
      {
        "builtIn": 1,
        "datasource": "Prometheus",
        "enable": true,
        "hide": true,
        "iconColor": "rgba(0, 211, 255, 1)",
        "name": "Annotations & Alerts",
        "target": {
          "limit": 100,
          "matchAny": false,
          "tags": [],
          "type": "dashboard"
        },
        "type": "dashboard"
      }
    ]
  },
  "editable": true,
  "fiscalYearStartMonth": 0,
  "graphTooltip": 0,
  "id": 2,
  "links": [],
  "liveNow": false,
  "panels": [
    {
      "gridPos": {
        "h": 6,
        "w": 4,
        "x": 0,
        "y": 0
      },
      "id": 8,
      "options": {
        "content": "<img src=\"https://upload.wikimedia.org/wikipedia/commons/c/c3/Python-logo-notext.svg\" alt=\"\" style='height: 100%; width: 100%; object-fit: contain'>",
        "mode": "html"
      },
      "pluginVersion": "8.3.3",
      "title": "Python 3.8.6",
      "type": "text"
    },
    {
      "fieldConfig": {
        "defaults": {
          "color": {
            "mode": "thresholds"
          },
          "mappings": [],
          "thresholds": {
            "mode": "absolute",
            "steps": [
              {
                "color": "green",
                "value": null
              },
              {
                "color": "semi-dark-yellow",
                "value": 100
              },
              {
                "color": "dark-orange",
                "value": 500
              },
              {
                "color": "dark-red",
                "value": 1000
              }
            ]
          }
        },
        "overrides": []
      },
      "gridPos": {
        "h": 6,
        "w": 12,
        "x": 4,
        "y": 0
      },
      "id": 4,
      "options": {
        "colorMode": "value",
        "graphMode": "none",
        "justifyMode": "auto",
        "orientation": "auto",
        "reduceOptions": {
          "calcs": [
            "lastNotNull"
          ],
          "fields": "",
          "values": false
        },
        "textMode": "auto"
      },
      "pluginVersion": "8.3.3",
      "targets": [
        {
          "datasource": {
            "type": "prometheus"
          },
          "exemplar": true,
          "expr": "sum(rate(starlette_requests_in_progress{path_template!~\"/metrics\", path_template!~\"/openapi.json|/docs|/\", method!~\"OPTIONS\"}[$__rate_interval]))",
          "interval": "",
          "legendFormat": "",
          "refId": "A"
        }
      ],
      "title": "Requests in progress",
      "type": "stat"
    },
    {
      "fieldConfig": {
        "defaults": {
          "color": {
            "mode": "palette-classic"
          },
          "custom": {
            "axisLabel": "",
            "axisPlacement": "auto",
            "barAlignment": 0,
            "drawStyle": "line",
            "fillOpacity": 0,
            "gradientMode": "none",
            "hideFrom": {
              "legend": false,
              "tooltip": false,
              "viz": false
            },
            "lineInterpolation": "smooth",
            "lineWidth": 1,
            "pointSize": 5,
            "scaleDistribution": {
              "type": "linear"
            },
            "showPoints": "auto",
            "spanNulls": false,
            "stacking": {
              "group": "A",
              "mode": "none"
            },
            "thresholdsStyle": {
              "mode": "off"
            }
          },
          "mappings": [],
          "thresholds": {
            "mode": "absolute",
            "steps": [
              {
                "color": "green",
                "value": null
              },
              {
                "color": "red",
                "value": 80
              }
            ]
          }
        },
        "overrides": []
      },
      "gridPos": {
        "h": 9,
        "w": 14,
        "x": 0,
        "y": 6
      },
      "id": 2,
      "options": {
        "legend": {
          "calcs": [
            "lastNotNull",
            "max"
          ],
          "displayMode": "table",
          "placement": "right",
          "sortBy": "Max",
          "sortDesc": true
        },
        "tooltip": {
          "mode": "single"
        }
      },
      "targets": [
        {
          "datasource": {
            "type": "prometheus"
          },
          "exemplar": true,
          "expr": "rate(starlette_requests_processing_time_seconds_count{path_template!~\"/metrics\", path_template!~\"/openapi.json|/docs|/\", method!~\"OPTIONS\"}[$__rate_interval])",
          "interval": "",
          "legendFormat": "{{method}}: {{path_template}}",
          "refId": "A"
        }
      ],
      "title": "Requests processing time",
      "type": "timeseries"
    },
    {
      "fieldConfig": {
        "defaults": {
          "color": {
            "mode": "palette-classic"
          },
          "custom": {
            "axisLabel": "",
            "axisPlacement": "auto",
            "barAlignment": 0,
            "drawStyle": "line",
            "fillOpacity": 0,
            "gradientMode": "none",
            "hideFrom": {
              "legend": false,
              "tooltip": false,
              "viz": false
            },
            "lineInterpolation": "smooth",
            "lineWidth": 1,
            "pointSize": 5,
            "scaleDistribution": {
              "type": "linear"
            },
            "showPoints": "auto",
            "spanNulls": false,
            "stacking": {
              "group": "A",
              "mode": "none"
            },
            "thresholdsStyle": {
              "mode": "off"
            }
          },
          "mappings": [],
          "thresholds": {
            "mode": "absolute",
            "steps": [
              {
                "color": "green",
                "value": null
              },
              {
                "color": "red",
                "value": 80
              }
            ]
          }
        },
        "overrides": []
      },
      "gridPos": {
        "h": 9,
        "w": 10,
        "x": 14,
        "y": 6
      },
      "id": 6,
      "options": {
        "legend": {
          "calcs": [
            "lastNotNull",
            "max"
          ],
          "displayMode": "table",
          "placement": "right",
          "sortBy": "Max",
          "sortDesc": true
        },
        "tooltip": {
          "mode": "single"
        }
      },
      "targets": [
        {
          "datasource": {
            "type": "prometheus",
            "uid": "PBFA97CFB590B2093"
          },
          "exemplar": true,
          "expr": "rate(starlette_responses_total{path_template!~\"/metrics\", path_template!~\"/openapi.json|/docs|/\", method!~\"OPTIONS\", status_code=~\"4..|5..\"}[$__rate_interval])",
          "hide": false,
          "interval": "",
          "legendFormat": "{{status_code}}: {{path_template}}",
          "refId": "A"
        }
      ],
      "thresholds": [],
      "title": "Errors",
      "type": "timeseries"
    }
  ],
  "refresh": "5s",
  "schemaVersion": 34,
  "style": "dark",
  "tags": [],
  "templating": {
    "list": []
  },
  "time": {
    "from": "now-5m",
    "to": "now"
  },
  "timepicker": {},
  "timezone": "",
  "title": "API",
  "uid": "pk1wdwTnk",
  "version": 2,
  "weekStart": ""
}